applepush
