Metadata-Version: 1.0
Name: applepush
Version: 0.0.2
Summary: 一个基于python2和http2的苹果推送SDK
Home-page: https://github.com/yubang/applepush
Author: yubang
Author-email: yubang93@gmail.com
License: UNKNOWN
Platform: UNKNOWN
